django_user_states/__init__.py
django_user_states/admin.py
django_user_states/apps.py
django_user_states/managers.py
django_user_states/models.py
django_user_states/tests.py
django_user_states/views.py
django_user_states/migrations/0001_initial.py
django_user_states/migrations/__init__.py
django_user_states-1.0.0.dist-info/LICENSE
django_user_states-1.0.0.dist-info/METADATA
django_user_states-1.0.0.dist-info/WHEEL
django_user_states-1.0.0.dist-info/top_level.txt
django_user_states-1.0.0.dist-info/RECORD
